Metadata-Version: 1.1
Name: django-money-rates
Version: 0.2.0
Summary: Currency conversion for money
Home-page: https://github.com/evonove/django-money-rates
Author: Federico Frenguelli
Author-email: synasius@gmail.com
License: BSD
Keywords: django-money-rates
Platform: UNKNOWN
Classifier: Development Status :: 2 - Pre-Alpha
Classifier: Framework :: Django
Classifier: Intended Audience :: Developers
Classifier: License :: OSI Approved :: BSD License
Classifier: Natural Language :: English
Classifier: Programming Language :: Python :: 2
Classifier: Programming Language :: Python :: 2.6
Classifier: Programming Language :: Python :: 2.7
Classifier: Programming Language :: Python :: 3
Classifier: Programming Language :: Python :: 3.3
